LICENSE
redditsfinder/__init__.py
redditsfinder/redditsfinder_utils.py
redditsfinder-2.1.3.dist-info/entry_points.txt
redditsfinder-2.1.3.dist-info/LICENSE
redditsfinder-2.1.3.dist-info/WHEEL
redditsfinder-2.1.3.dist-info/METADATA
redditsfinder-2.1.3.dist-info/RECORD
