Metadata-Version: 2.1
Name: redditsfinder
Version: 2.1.3
Summary: Archive a reddit user's post history. Formatted overview of a profile, JSON containing every post, and picture downloads.
Home-page: https://github.com/Fitzy1293/redditsfinder
License: MIT
Keywords: reddit,webscraping,reddit-crawler,pushshift
Author: fitzy1293
Author-email: berkshiremind@gmail.com
Requires-Python: >=3.7,<4.0
Classifier: License :: OSI Approved :: MIT License
Classifier: Programming Language :: Python :: 3
Classifier: Programming Language :: Python :: 3.10
Classifier: Programming Language :: Python :: 3.7
Classifier: Programming Language :: Python :: 3.8
Classifier: Programming Language :: Python :: 3.9
Requires-Dist: requests (>=2.28.1,<3.0.0)
Requires-Dist: rich (>=12.5.1,<13.0.0)
Project-URL: Repository, https://github.com/Fitzy1293/redditsfinder
